func_analysis/__init__.py
func_analysis/custom_types.py
func_analysis/decorators.py
func_analysis/interval_util.py
func_analysis/analyzed_func/__init__.py
func_analysis/analyzed_func/af_base.py
func_analysis/analyzed_func/af_crits_pois.py
func_analysis/analyzed_func/af_intervals_extrema.py
func_analysis/analyzed_func/af_symmetry.py
func_analysis/analyzed_func/af_zeros.py
func_analysis/analyzed_func/analyzed_func.py
func_analysis-0.3.0.dist-info/LICENSE
func_analysis-0.3.0.dist-info/METADATA
func_analysis-0.3.0.dist-info/WHEEL
func_analysis-0.3.0.dist-info/top_level.txt
func_analysis-0.3.0.dist-info/RECORD
