Metadata-Version: 2.1
Name: func-analysis
Version: 0.3.0
Summary: Analyze function behavior using introductory calculus.
Home-page: https://gitlab.com/Seirdy/func-analysis
Author: Rohan Kumar
Author-email: seirdy@pm.ch
License: AGPLv3+
Keywords: func-analysis,calculus,math
Platform: UNKNOWN
Classifier: License :: OSI Approved :: GNU Affero General Public License v3 or later (AGPLv3+)
Classifier: Operating System :: OS Independent
Classifier: Development Status :: 2 - Pre-Alpha
Classifier: Programming Language :: Python
Classifier: Programming Language :: Python :: 3.7
Classifier: Programming Language :: Python :: 3 :: Only
Classifier: Programming Language :: Python :: Implementation :: CPython
Classifier: Topic :: Scientific/Engineering :: Mathematics
Classifier: Natural Language :: English
Classifier: Intended Audience :: Developers
Classifier: Intended Audience :: Education
Requires-Dist: mpmath
Requires-Dist: numpy
Requires-Dist: scipy
